README.rst
setup.py
src/nodeconductor_aws/__init__.py
src/nodeconductor_aws/admin.py
src/nodeconductor_aws/apps.py
src/nodeconductor_aws/backend.py
src/nodeconductor_aws/cost_tracking.py
src/nodeconductor_aws/executors.py
src/nodeconductor_aws/extension.py
src/nodeconductor_aws/filters.py
src/nodeconductor_aws/models.py
src/nodeconductor_aws/serializers.py
src/nodeconductor_aws/tasks.py
src/nodeconductor_aws/urls.py
src/nodeconductor_aws/views.py
src/nodeconductor_aws.egg-info/PKG-INFO
src/nodeconductor_aws.egg-info/SOURCES.txt
src/nodeconductor_aws.egg-info/dependency_links.txt
src/nodeconductor_aws.egg-info/entry_points.txt
src/nodeconductor_aws.egg-info/not-zip-safe
src/nodeconductor_aws.egg-info/requires.txt
src/nodeconductor_aws.egg-info/top_level.txt
src/nodeconductor_aws/management/__init__.py
src/nodeconductor_aws/management/commands/__init__.py
src/nodeconductor_aws/management/commands/export_ami_catalog.py
src/nodeconductor_aws/management/commands/import_ami_catalog.py
src/nodeconductor_aws/migrations/0001_initial.py
src/nodeconductor_aws/migrations/0002_remove_awsservice_name.py
src/nodeconductor_aws/migrations/0003_update_ip_addresses.py
src/nodeconductor_aws/migrations/0004_remove_volume_start_time.py
src/nodeconductor_aws/migrations/0005_instance_size_backend_id.py
src/nodeconductor_aws/migrations/__init__.py